xbandits/__init__.py
xbandits/algo/__init__.py
xbandits/algo/ucb.py
xbandits/core/__init__.py
xbandits/core/regret.py
xbandits/core/rollout.py
xbandits/core/statistics.py
xbandits-0.0.1.dist-info/LICENSE
xbandits-0.0.1.dist-info/METADATA
xbandits-0.0.1.dist-info/WHEEL
xbandits-0.0.1.dist-info/top_level.txt
xbandits-0.0.1.dist-info/RECORD
